st_editor/__init__.py
st_editor/frontend/index.html
st_editor/frontend/main.js
st_editor/frontend/streamlit-component-lib.js
st_editor/frontend/style.css
streamlit_editor-0.0.3.dist-info/LICENSE
streamlit_editor-0.0.3.dist-info/METADATA
streamlit_editor-0.0.3.dist-info/WHEEL
streamlit_editor-0.0.3.dist-info/top_level.txt
streamlit_editor-0.0.3.dist-info/RECORD
